django_unravel/__init__.py
django_unravel/mail/__init__.py
django_unravel/mail/backends/__init__.py
django_unravel/mail/backends/filebased.py
django_unravel/templates/django_unravel/email.html
sample/__init__.py
sample/asgi.py
sample/settings.py
sample/urls.py
sample/wsgi.py
django_unravel-0.1.1.dist-info/LICENSE
django_unravel-0.1.1.dist-info/METADATA
django_unravel-0.1.1.dist-info/WHEEL
django_unravel-0.1.1.dist-info/top_level.txt
django_unravel-0.1.1.dist-info/RECORD
